{
    "type": "object",
    "properties": {
        "subscriptionId": {
            "required": true,
            "type": "string"
        },
        "resourceGroupName": {
            "required": true,
            "type": "string"
        },
        "labName": {
            "required": true,
            "type": "string"
        },
        "name": {
            "required": true,
            "type": "string"
        },
        "requestBody": {
            "description": "Request body for resizing a virtual machine.",
            "properties": {
                "size": {
                    "description": "Specifies the size of the virtual machine.",
                    "type": "string"
                }
            },
            "type": "object"
        },
        "api_version": {
            "required": true,
            "type": "string",
            "default": "2018-09-15"
        }
    }
}